sign_prosody_extraction/__init__.py
sign_prosody_extraction/cli.py
sign_prosody_extraction/export.py
sign_prosody_extraction/plot.py
sign_prosody_extraction/targets.py
sign_prosody_extraction/typing.py
sign_prosody_extraction/visualize.py
sign_prosody_extraction/articulator/__init__.py
sign_prosody_extraction/articulator/cotracker.py
sign_prosody_extraction/articulator/mediapipe.py
sign_prosody_extraction/img/dir_scale.png
sign_prosody_extraction/img/dir_scale.svg
sign_prosody_extraction-24.12.dist-info/METADATA
sign_prosody_extraction-24.12.dist-info/WHEEL
sign_prosody_extraction-24.12.dist-info/entry_points.txt
sign_prosody_extraction-24.12.dist-info/licenses/LICENSE
sign_prosody_extraction-24.12.dist-info/RECORD
