Metadata-Version: 2.4
Name: sign-prosody-extraction
Version: 24.12
Summary: Code and command-line tool for "Automated Extraction of Prosodic Structure from Unannotated Sign Language Video" (Sevilla et al., 2024).
Project-URL: Repository, https://github.com/agarsev/sign-prosody-extraction
Author-email: "Antonio F. G. Sevilla" <afgs@ucm.es>
License: EUPL-1.2
License-File: LICENSE
Requires-Python: ==3.10.*
Requires-Dist: click>=8.1.7
Requires-Dist: flow-vis>=0.1
Requires-Dist: imageio[ffmpeg]>=2.34.0
Requires-Dist: matplotlib>=3.8.4
Requires-Dist: mediapipe>=0.10.11
Requires-Dist: nptyping>=2.5.0
Requires-Dist: numpy>=1.26.4
Requires-Dist: pandas>=2.2.2
Requires-Dist: scikit-learn>=1.4.2
Requires-Dist: scipy>=1.13.0
Requires-Dist: torch>=2.2.2
Requires-Dist: torchvision>=0.17.2
